LICENSE
MANIFEST.in
README.rst
pyproject.toml
setup.cfg
setup.py
docs/conf.py
qocttools/__init__.py
qocttools/cythonfuncs.c
qocttools/cythonfuncs.pyx
qocttools/floquet.py
qocttools/hamiltonians.py
qocttools/krotov.py
qocttools/liouville.py
qocttools/math_extra.py
qocttools/pulses.py
qocttools/qoct.py
qocttools/solvers.py
qocttools/target.py
qocttools.egg-info/PKG-INFO
qocttools.egg-info/SOURCES.txt
qocttools.egg-info/dependency_links.txt
qocttools.egg-info/requires.txt
qocttools.egg-info/top_level.txt
qocttools/models/GdW30.py
qocttools/models/__init__.py
qocttools/models/graphene.py
qocttools/models/hBN.py
qocttools/models/tmd.py
qocttools/sampleruns/floquet/Ax0
qocttools/sampleruns/floquet/Ay0
qocttools/sampleruns/floquet/data.ref
qocttools/sampleruns/floquet/floquet.ipynb
qocttools/sampleruns/gradient-U/data.ref
qocttools/sampleruns/gradient-U/eigenstates.qu
qocttools/sampleruns/gradient-U/gradient-U.ipynb
qocttools/sampleruns/gradient-psi/data.ref
qocttools/sampleruns/gradient-psi/eigenstates.qu
qocttools/sampleruns/gradient-psi/gradient-psi.ipynb
qocttools/sampleruns/gradient-rho/V
qocttools/sampleruns/gradient-rho/data.ref
qocttools/sampleruns/gradient-rho/eigenstates.qu
qocttools/sampleruns/gradient-rho/gradient-rho.ipynb
qocttools/sampleruns/propagators-U/data.ref
qocttools/sampleruns/propagators-U/eigenstates.qu
qocttools/sampleruns/propagators-U/propagators-U.ipynb
qocttools/sampleruns/propagators-psi/data.ref
qocttools/sampleruns/propagators-psi/eigenstates.qu
qocttools/sampleruns/propagators-psi/propagators-psi.ipynb
qocttools/sampleruns/propagators-rho/data.ref
qocttools/sampleruns/propagators-rho/eigenstates.qu
qocttools/sampleruns/propagators-rho/propagators-rho.ipynb
qocttools/sampleruns/qoctbasic/V
qocttools/sampleruns/qoctbasic/data.ref
qocttools/sampleruns/qoctbasic/qoctbasic.ipynb
qocttools/sampleruns/rotations/data.ref
qocttools/sampleruns/rotations/rotations.ipynb
qocttools/tests/__init__.py
qocttools/tests/short.py