Metadata-Version: 2.1
Name: qocttools
Version: 0.0.14
Summary: A set of tools to do quantum optimal control calculations
Author-email: Alberto Castro <alberto.castro.barrigon@gmail.com>
Project-URL: Homepage, https://qocttools.readthedocs.io/
Classifier: Programming Language :: Python :: 3
Classifier: License :: OSI Approved :: GNU General Public License v3 (GPLv3)
Classifier: Operating System :: OS Independent
Requires-Python: >=3.9
License-File: LICENSE
Requires-Dist: pytest>=7.4.0
Requires-Dist: pytest-xdist>=3.3.1
Requires-Dist: numpy>=1.25.1
Requires-Dist: jupyter>=1.0.0
Requires-Dist: scipy>=1.11.1
Requires-Dist: qutip>=5.0.0
Requires-Dist: qutip-qip>=0.3.0
Requires-Dist: qutip-qtrl>=0.1.0
Requires-Dist: nlopt>=2.7.1
Requires-Dist: matplotlib>=3.7.2
Requires-Dist: python-git-info>=0.8.3
Requires-Dist: mpi4py>=3.1.4
Requires-Dist: jaxlib>=0.4.13
Requires-Dist: jax>=0.4.13
Requires-Dist: sphinx>=6.2.1
Requires-Dist: nbsphinx>=0.9.2
Requires-Dist: sphinxcontrib-bibtex>=2.5.0
Requires-Dist: sphinx-rtd-theme>=1.2.2
